kaiju_kafka/__init__.py
kaiju_kafka/services.py
kaiju_kafka/streams.py
kaiju_kafka/tests/__init__.py
kaiju_kafka/tests/fixtures.py
kaiju_kafka/tests/test_streams.py
kaiju_kafka-2.0.1.dist-info/LICENSE
kaiju_kafka-2.0.1.dist-info/METADATA
kaiju_kafka-2.0.1.dist-info/WHEEL
kaiju_kafka-2.0.1.dist-info/top_level.txt
kaiju_kafka-2.0.1.dist-info/RECORD
